allegro_api/__init__.py
allegro_api/api_client.py
allegro_api/configuration.py
allegro_api/exceptions.py
allegro_api/rest.py
allegro_api/api/__init__.py
allegro_api/api/additional_services_api.py
allegro_api/api/after_sale_services_api.py
allegro_api/api/auctions_and_bidding_api.py
allegro_api/api/badge_campaigns_api.py
allegro_api/api/batch_offer_modification_api.py
allegro_api/api/billing_api.py
allegro_api/api/blacklist_management_api.py
allegro_api/api/categories_and_parameters_api.py
allegro_api/api/classifieds_api.py
allegro_api/api/compatibility_list_api.py
allegro_api/api/contacts_api.py
allegro_api/api/delivery_api.py
allegro_api/api/disputes_api.py
allegro_api/api/images_and_attachments_api.py
allegro_api/api/information_about_user_api.py
allegro_api/api/offer_management_api.py
allegro_api/api/offer_rating_api.py
allegro_api/api/offer_tags_api.py
allegro_api/api/offer_variants_api.py
allegro_api/api/order_management_api.py
allegro_api/api/payments_api.py
allegro_api/api/points_of_service_api.py
allegro_api/api/pricing_api.py
allegro_api/api/products_api.py
allegro_api/api/promotion_campaigns_api.py
allegro_api/api/public_offer_information_api.py
allegro_api/api/public_user_information_api.py
allegro_api/api/sets_and_rebates_api.py
allegro_api/api/size_tables_api.py
allegro_api/api/users_offer_information_api.py
allegro_api/models/__init__.py
allegro_api/models/additional_email.py
allegro_api/models/additional_email_request.py
allegro_api/models/additional_emails_response.py
allegro_api/models/additional_service_definition_request.py
allegro_api/models/additional_service_request.py
allegro_api/models/additional_service_response.py
allegro_api/models/additional_services_group.py
allegro_api/models/additional_services_group_request.py
allegro_api/models/additional_services_group_response.py
allegro_api/models/additional_services_groups.py
allegro_api/models/address.py
allegro_api/models/after_sales_services.py
allegro_api/models/answer.py
allegro_pl_rest_api-2020.3.12.dist-info/METADATA
allegro_pl_rest_api-2020.3.12.dist-info/WHEEL
allegro_pl_rest_api-2020.3.12.dist-info/top_level.txt
allegro_pl_rest_api-2020.3.12.dist-info/RECORD
