Metadata-Version: 2.1
Name: allegro-pl-rest-api
Version: 2020.3.12
Summary: Allegro REST API
Home-page: UNKNOWN
Author: API Support
Author-email: team@openapitools.org
License: UNKNOWN
Keywords: OpenAPI,OpenAPI-Generator,Allegro REST API
Platform: UNKNOWN
Requires-Dist: urllib3 (>=1.15)
Requires-Dist: six (>=1.10)
Requires-Dist: certifi
Requires-Dist: python-dateutil
